steel_ewc_test/__init__.py
steel_ewc_test/evaluate.py
steel_ewc_test/main.py
steel_ewc_test/test.py
steel_ewc_test/train.py
steel_ewc_test/datasets/TimeDataset.py
steel_ewc_test/datasets/__init__.py
steel_ewc_test/models/CNN.py
steel_ewc_test/models/GDN.py
steel_ewc_test/models/GRU.py
steel_ewc_test/models/LSTM.py
steel_ewc_test/models/LSTMVAE.py
steel_ewc_test/models/MLP.py
steel_ewc_test/models/RNN.py
steel_ewc_test/models/Transformer.py
steel_ewc_test/models/__init__.py
steel_ewc_test/scripts/__init__.py
steel_ewc_test/scripts/process_steel.py
steel_ewc_test/show_img/__init__.py
steel_ewc_test/util/__init__.py
steel_ewc_test/util/data.py
steel_ewc_test/util/env.py
steel_ewc_test/util/ewc.py
steel_ewc_test/util/ewc_utils.py
steel_ewc_test/util/iostream.py
steel_ewc_test/util/loss_func.py
steel_ewc_test/util/net_struct.py
steel_ewc_test/util/preprocess.py
steel_ewc_test/util/util_time.py
steel_ewc_test-0.0.7.dist-info/LICENSE
steel_ewc_test-0.0.7.dist-info/METADATA
steel_ewc_test-0.0.7.dist-info/WHEEL
steel_ewc_test-0.0.7.dist-info/top_level.txt
steel_ewc_test-0.0.7.dist-info/RECORD
