Metadata-Version: 2.1
Name: steel-ewc-test
Version: 0.0.7
Summary: steel ewc test package
Author: pyd
Author-email: panydacademy@163.com
Requires-Python: >=3.6
License-File: LICENSE
